[{"model": "repair.repairstatus", "pk": 1, "fields": {"name": "Recepcionada", "description": "Su maquinaria se encuentra en nuestras instalaciones a la espera de la realizaci\u00f3n del presupuesto", "percentage": 25}}, {"model": "repair.repairstatus", "pk": 2, "fields": {"name": "Enviada al fabricante", "description": "Su maquinaria ha sido enviada al fabricante para su reparaci\u00f3n", "percentage": 65}}, {"model": "repair.repairstatus", "pk": 3, "fields": {"name": "Pendiente de aceptar presupuesto", "description": "Debe confirmarnos si acepta o no el presupuesto para poder proseguir con su reparaci\u00f3n", "percentage": 65}}, {"model": "repair.repairstatus", "pk": 4, "fields": {"name": "Presupuesto aceptado", "description": "Ha aceptado el presupuesto y proseguimos con su reparaci\u00f3n", "percentage": 80}}, {"model": "repair.repairstatus", "pk": 5, "fields": {"name": "Pendiente de material del fabricante", "description": "Estamos pendientes de material por parte del fabricante para poder proseguir su reparaci\u00f3n", "percentage": 50}}, {"model": "repair.repairstatus", "pk": 6, "fields": {"name": "Reparada", "description": "Su m\u00e1quina se encuentra reparada, puede pasar a recogerla", "percentage": 100}}, {"model": "repair.repairstatus", "pk": 7, "fields": {"name": "Entregada", "description": "La reparaci\u00f3n se ha completado", "percentage": 100}}, {"model": "repair.repairstatus", "pk": 8, "fields": {"name": "Entregada sin reparar", "description": "La reparaci\u00f3n se ha cancelado", "percentage": -100}}, {"model": "repair.repairstatus", "pk": 9, "fields": {"name": "Presupuesto no aceptado", "description": "No ha aceptado el presupuesto. Puede pasar a recoger la maquinaria sin reparar.", "percentage": -100}}, {"model": "repair.repairstatus", "pk": 10, "fields": {"name": "Material de fabricante recibido", "description": "Recibido nuevo material para seguir con su reparaci\u00f3n.", "percentage": 70}}]